{
  "node_id": 22,
  "name": "Logistic Regression",
  "category": 11,
  "node_type": 0,
  "family": 6,
  "compatible_with_stream": false,
  "compatible_stream_output_modes": [],
  "compatible_with_spark_pipeline": true,
  "is_splitter": false,
  "produces_model": true,
  "estimator_name": "LogisticRegression",
  "parameter_props": {"featuresCol": {"type": ["string"], "constraints":[], "default":"features"}, "labelCol": {"type": ["string"], "constraints":[], "default":"label"}, "predictionCol": {"type": ["string"], "constraints":[], "default":"prediction"},"maxIter": {"type": ["int"], "constraints":[1], "default":"100"},"elasticNetParam": {"type": ["double"], "constraints":[16], "default":"0.0"},"regParam": {"type": ["double"], "constraints":[4], "default":"100"},
    "tol": {"type": ["double"], "constraints":[7], "default":"1e-06"},
    "fitIntercept": {"type": ["bool"], "constraints":[], "default":"True"},
    "threshold": {"type": ["double"], "constraints":[10], "default":"0.5"},
    "probabilityCol": {"type": ["string"], "constraints":[], "default":"probability"},
    "rawPredictionCol": {"type": ["string"], "constraints":[], "default":"rawPrediction"},
    "standardization": {"type": ["bool"], "constraints":[], "default":"True"},
    "weightCol": {"type": ["double"], "constraints":[], "default":"1.0"},
    "aggregationDepth": {"type": ["int"], "constraints":[13], "default":"2"},
    "family": {"type": ["string"], "constraints":[19], "default":"auto"}},
  "df_constraints": [0,1,2,4,5,8,10,13],
  "explanation": "family: The name of family which is a description of the label distribution to be used in the model. Supported options: auto, binomial, multinomial. Added  rawPrediction, probability and prediction columns to schema."
}